openz/__init__.py
openz/_core.py
openz-0.1.2.dist-info/LICENSE
openz-0.1.2.dist-info/METADATA
openz-0.1.2.dist-info/WHEEL
openz-0.1.2.dist-info/RECORD
