Metadata-Version: 2.1
Name: openz
Version: 0.1.2
Summary: 
Home-page: https://github.com/Cologler/openz-python
License: MIT
Author: Cologler
Author-email: skyoflw@gmail.com
Requires-Python: >=3.8,<4.0
Classifier: License :: OSI Approved :: MIT License
Classifier: Programming Language :: Python :: 3
Classifier: Programming Language :: Python :: 3.8
Classifier: Programming Language :: Python :: 3.9
Classifier: Programming Language :: Python :: 3.10
Classifier: Programming Language :: Python :: 3.11
Requires-Dist: filelock (>=3.12.0,<4.0.0)
Requires-Dist: nanoid (>=2.0.0,<3.0.0)
Requires-Dist: portalocker (>=2.7.0,<3.0.0)
